{"accuracy": 0.78, "correct_count": 78, "total_count": 100}
{"id": 12, "valid": false, "model_name": "gpt-3.5-turbo-0125", "test_category": "executable_simple", "error": ["Failed to decode executable. 'Name' object has no attribute 'elts'"], "error_type": "executable_decoder:decoder_failed", "prompt": {"question": "In a physics experiment, a ball is dropped from a height with an initial velocity of 0 m/s. If the acceleration due to gravity is considered as 9.8 m/s\u00b2 and the ball is in free fall for 7 seconds, can the 'calculate_final_velocity' function be used to ascertain the final velocity of the ball at the end of this time period?", "function": {"name": "calculate_final_velocity", "description": "Calculates the final velocity of an object.", "parameters": {"type": "dict", "properties": {"initial_velocity": {"type": "integer", "description": "The initial velocity of the object."}, "acceleration": {"type": "float", "description": "The acceleration of the object."}, "time": {"type": "integer", "description": "The time the object has been moving."}}, "required": ["initial_velocity", "acceleration", "time"]}}, "execution_result": [68.60000000000001], "execution_result_type": "exact_match"}, "model_result_raw": "NO"}
{"id": 13, "model_name": "gpt-3.5-turbo-0125", "test_category": "executable_simple", "valid": false, "error": ["Wrong execution result for: 'calculate_future_value(present_value=5000,interest_rate=5,periods=10)'. Expected: 5025.056325065662, but got: 8144.47313388721."], "error_type": "executable_checker:wrong_result", "prompt": {"question": "In a financial scenario, suppose you have invested $5000 in a fixed deposit scheme that offers an annual interest rate of 5%. If you plan to keep the money in the deposit for 10 years, can you determine the value of your investment at the end of this period?", "function": {"name": "calculate_future_value", "description": "Calculates the future value of an investment.", "parameters": {"type": "dict", "properties": {"present_value": {"type": "integer", "description": "The present value of the investment."}, "interest_rate": {"type": "integer", "description": "The interest rate of the investment."}, "periods": {"type": "integer", "description": "The number of periods."}}, "required": ["present_value", "interest_rate", "periods"]}}, "execution_result": [5025.056325065662], "execution_result_type": "exact_match"}, "model_result_raw": "[calculate_future_value(present_value=5000, interest_rate=5, periods=10)]", "model_result_decoded": ["calculate_future_value(present_value=5000,interest_rate=5,periods=10)"]}
{"id": 25, "valid": false, "model_name": "gpt-3.5-turbo-0125", "test_category": "executable_simple", "error": ["Failed to decode executable. 'BinOp' object is not subscriptable"], "error_type": "executable_decoder:decoder_failed", "prompt": {"question": "As a physics student, you are studying the motion of a particle moving along a straight line. The position of the particle at any time 'x' is given by the function f(x) = 3t^2 + 2x + 1. You are interested in understanding the velocity of the particle at a specific time, say t = 5 seconds.", "function": {"name": "estimate_derivative", "description": "Estimate the derivative of a function at a given point.", "parameters": {"type": "dict", "properties": {"function": {"type": "string", "description": "The function to calculate the derivative of. This should be in the format of python lambda function."}, "x": {"type": "integer", "description": "The point to calculate the derivative at."}}, "required": ["function", "x"]}}, "execution_result": [32.00000264769187], "execution_result_type": "exact_match"}, "model_result_raw": "[estimate_derivative(function=lambda t: 3*t**2 + 2*5 + 1, x=5)]"}
{"id": 26, "valid": false, "model_name": "gpt-3.5-turbo-0125", "test_category": "executable_simple", "error": ["Failed to decode executable. 'BinOp' object is not subscriptable"], "error_type": "executable_decoder:decoder_failed", "prompt": {"question": "As a financial analyst, you are studying the growth of a company's revenue over time. The revenue of the company at any time 'x' is given by the function f(x) = 4x^3 + 3x^2 + 2x + 1. You are interested in understanding the rate of change of the company's revenue at a specific time, say t = 7 years.", "function": {"name": "estimate_derivative", "description": "Estimate the derivative of a function at a given point.", "parameters": {"type": "dict", "properties": {"function": {"type": "string", "description": "The function to calculate the derivative of.This should be in the format of python lambda function."}, "x": {"type": "integer", "description": "The point to calculate the derivative at."}}, "required": ["function", "x"]}}, "execution_result": [632.0010470517445], "execution_result_type": "exact_match"}, "model_result_raw": "[estimate_derivative(function=lambda x: 4*x**3 + 3*x**2 + 2*x + 1, x=7)]"}
{"id": 33, "valid": false, "model_name": "gpt-3.5-turbo-0125", "test_category": "executable_simple", "error": ["Failed to decode executable. invalid syntax (<unknown>, line 1)"], "error_type": "executable_decoder:decoder_failed", "prompt": {"question": "As a financial analyst, you are researching the company behind the stock named 'AAPL'.", "function": {"name": "get_company_name_by_stock_name", "description": "Finds the company name of a stock by its stock name.", "parameters": {"type": "dict", "properties": {"stock_name": {"type": "string", "description": "The stock name of the product."}}, "required": ["stock_name"]}}, "execution_result": ["Apple Inc."], "execution_result_type": "pattern_match"}, "model_result_raw": "tools call: \n[get_company_name_by_stock_name(stock_name='AAPL')]"}
{"id": 37, "model_name": "gpt-3.5-turbo-0125", "test_category": "executable_simple", "valid": false, "error": ["Wrong number of functions provided."], "error_type": "value_error:exec_result_count", "prompt": {"question": "As a travel agent, you have a client who is interested in visiting the city of 'Paris'. Could you determine the geographical coordinates of 'Paris' by providing 'Paris' as the city name?", "function": {"name": "get_coordinates_from_city", "description": "Fetches the latitude and longitude of a given city name using the Maps.co Geocoding API.", "parameters": {"type": "dict", "properties": {"city_name": {"type": "string", "description": "The name of the city."}}, "required": ["city_name"]}}, "execution_result": ["48.8588897", "2.3200410217200766"], "execution_result_type": "exact_match"}, "model_result_raw": "[get_coordinates_from_city(city_name='Paris')]", "model_result_decoded": ["get_coordinates_from_city(city_name='Paris')"]}
{"id": 38, "model_name": "gpt-3.5-turbo-0125", "test_category": "executable_simple", "valid": false, "error": ["Wrong number of functions provided."], "error_type": "value_error:exec_result_count", "prompt": {"question": "As a wildlife researcher, you are planning to study the migration patterns of a certain bird species in 'Cairo'. Can you find the exact latitude and longitude of 'Cairo' by inputting 'Cairo' as the city name?", "function": {"name": "get_coordinates_from_city", "description": "Fetches the latitude and longitude of a given city name using the Maps.co Geocoding API.", "parameters": {"type": "dict", "properties": {"city_name": {"type": "string", "description": "The name of the city."}}, "required": ["city_name"]}}, "execution_result": ["30.0443879", "31.2357257"], "execution_result_type": "exact_match"}, "model_result_raw": "[get_coordinates_from_city(city_name='Cairo')]", "model_result_decoded": ["get_coordinates_from_city(city_name='Cairo')"]}
{"id": 55, "model_name": "gpt-3.5-turbo-0125", "test_category": "executable_simple", "valid": false, "error": ["Worng type for: \"get_stock_price_by_stock_name(stock_name='Apple Inc.')\". Expected type: <class 'str'>, but got: <class 'dict'>."], "error_type": "executable_checker:wrong_result_type", "prompt": {"question": "As an investment advisor, you are required to analyze the current price of Apple Inc.'s stock.", "function": {"name": "get_stock_price_by_stock_name", "description": "Finds the price of a stock by its stock name.", "parameters": {"type": "dict", "properties": {"stock_name": {"type": "string", "description": "The stock name of the product."}}, "required": ["stock_name"]}}, "execution_result": ["$193.49"], "execution_result_type": "pattern_match"}, "model_result_raw": "[get_stock_price_by_stock_name(stock_name='Apple Inc.')]", "model_result_decoded": ["get_stock_price_by_stock_name(stock_name='Apple Inc.')"]}
{"id": 56, "model_name": "gpt-3.5-turbo-0125", "test_category": "executable_simple", "valid": false, "error": ["Worng type for: \"get_stock_price_by_stock_name(stock_name='Microsoft Corporation')\". Expected type: <class 'str'>, but got: <class 'dict'>."], "error_type": "executable_checker:wrong_result_type", "prompt": {"question": "As a financial analyst, you are tasked with monitoring the stock market performance of Microsoft Corporation.", "function": {"name": "get_stock_price_by_stock_name", "description": "Finds the price of a stock by its stock name.", "parameters": {"type": "dict", "properties": {"stock_name": {"type": "string", "description": "The stock name of the product."}}, "required": ["stock_name"]}}, "execution_result": ["$403.34"], "execution_result_type": "pattern_match"}, "model_result_raw": "[get_stock_price_by_stock_name(stock_name='Microsoft Corporation')]", "model_result_decoded": ["get_stock_price_by_stock_name(stock_name='Microsoft Corporation')"]}
{"id": 71, "valid": false, "model_name": "gpt-3.5-turbo-0125", "test_category": "executable_simple", "error": ["Failed to decode executable. "], "error_type": "executable_decoder:decoder_failed", "prompt": {"question": "As a financial advisor, you are helping a client understand their potential mortgage payments. The client is considering a loan amount of $350,000 with an interest rate of 3.5% over a loan period of 30 years. Can you use the 'mortgage_calculator' function with 'loan_amount' as 350000, 'interest_rate' as 3.5, and 'loan_period' as 30 to calculate the monthly mortgage payment?", "function": {"name": "mortgage_calculator", "description": "Calculates the monthly mortgage payment.", "parameters": {"type": "dict", "properties": {"loan_amount": {"type": "integer", "description": "The amount of the loan."}, "interest_rate": {"type": "float", "description": "The interest rate of the loan."}, "loan_period": {"type": "integer", "description": "The period of the loan."}}, "required": ["loan_amount", "interest_rate", "loan_period"]}}, "execution_result": [1571.656407330882], "execution_result_type": "exact_match"}, "model_result_raw": "[{'mortgage_calculator': {'loan_amount': 350000, 'interest_rate': 3.5, 'loan_period': 30}}]"}
{"id": 72, "valid": false, "model_name": "gpt-3.5-turbo-0125", "test_category": "executable_simple", "error": ["Failed to decode executable. invalid syntax (<unknown>, line 1)"], "error_type": "executable_decoder:decoder_failed", "prompt": {"question": "As a real estate agent, you are assisting a couple in understanding their potential monthly mortgage payments. They are looking at a property valued at $500,000 and are considering a loan with an interest rate of 4.5% for a period of 25 years. Can you use the 'mortgage_calculator' function with 'loan_amount' as 500000, 'interest_rate' as 4.5, and 'loan_period' as 25 to determine what their monthly mortgage payment would be?", "function": {"name": "mortgage_calculator", "description": "Calculates the monthly mortgage payment.", "parameters": {"type": "dict", "properties": {"loan_amount": {"type": "integer", "description": "The amount of the loan."}, "interest_rate": {"type": "float", "description": "The interest rate of the loan."}, "loan_period": {"type": "integer", "description": "The period of the loan."}}, "required": ["loan_amount", "interest_rate", "loan_period"]}}, "execution_result": [2779.1623898099774], "execution_result_type": "exact_match"}, "model_result_raw": "[{'mortgage_calculator': loan_amount=500000, interest_rate=4.5, loan_period=25}]"}
{"id": 77, "model_name": "gpt-3.5-turbo-0125", "test_category": "executable_simple", "valid": false, "error": ["Wrong execution result for: \"retrieve_holiday_by_year(year='2010',country='FR')\". Expected: [{'date': '2010-01-01', 'localName': \"Jour de l'an\", 'name': \"New Year's Day\", 'countryCode': 'FR', 'fixed': True, 'global': True, 'counties': None, 'launchYear': 1967, 'types': ['Public']}, {'date': '2010-04-05', 'localName': 'Lundi de P\u00e2ques', 'name': 'Easter Monday', 'countryCode': 'FR', 'fixed': False, 'global': True, 'counties': None, 'launchYear': 1642, 'types': ['Public']}, {'date': '2010-05-01', 'localName': 'F\u00eate du Travail', 'name': 'Labour Day', 'countryCode': 'FR', 'fixed': True, 'global': True, 'counties': None, 'launchYear': None, 'types': ['Public']}, {'date': '2010-05-08', 'localName': 'Victoire 1945', 'name': 'Victory in Europe Day', 'countryCode': 'FR', 'fixed': True, 'global': True, 'counties': None, 'launchYear': None, 'types': ['Public']}, {'date': '2010-05-13', 'localName': 'Ascension', 'name': 'Ascension Day', 'countryCode': 'FR', 'fixed': False, 'global': True, 'counties': None, 'launchYear': None, 'types': ['Public']}, {'date': '2010-05-24', 'localName': 'Lundi de Pentec\u00f4te', 'name': 'Whit Monday', 'countryCode': 'FR', 'fixed': False, 'global': True, 'counties': None, 'launchYear': None, 'types': ['Public']}, {'date': '2010-07-14', 'localName': 'F\u00eate nationale', 'name': 'Bastille Day', 'countryCode': 'FR', 'fixed': True, 'global': True, 'counties': None, 'launchYear': None, 'types': ['Public']}, {'date': '2010-08-15', 'localName': 'Assomption', 'name': 'Assumption Day', 'countryCode': 'FR', 'fixed': True, 'global': True, 'counties': None, 'launchYear': None, 'types': ['Public']}, {'date': '2010-11-01', 'localName': 'Toussaint', 'name': \"All Saints' Day\", 'countryCode': 'FR', 'fixed': True, 'global': True, 'counties': None, 'launchYear': None, 'types': ['Public']}, {'date': '2010-11-11', 'localName': 'Armistice 1918', 'name': 'Armistice Day', 'countryCode': 'FR', 'fixed': True, 'global': True, 'counties': None, 'launchYear': None, 'types': ['Public']}, {'date': '2010-12-25', 'localName': 'No\u00ebl', 'name': 'Christmas Day', 'countryCode': 'FR', 'fixed': True, 'global': True, 'counties': None, 'launchYear': None, 'types': ['Public']}], but got: [{'date': '2010-01-01', 'localName': \"Jour de l'an\", 'name': \"New Year's Day\", 'countryCode': 'FR', 'fixed': False, 'global': True, 'counties': None, 'launchYear': None, 'types': ['Public']}, {'date': '2010-04-05', 'localName': 'Lundi de P\u00e2ques', 'name': 'Easter Monday', 'countryCode': 'FR', 'fixed': False, 'global': True, 'counties': None, 'launchYear': None, 'types': ['Public']}, {'date': '2010-05-01', 'localName': 'F\u00eate du Travail', 'name': 'Labour Day', 'countryCode': 'FR', 'fixed': False, 'global': True, 'counties': None, 'launchYear': None, 'types': ['Public']}, {'date': '2010-05-08', 'localName': 'Victoire 1945', 'name': 'Victory in Europe Day', 'countryCode': 'FR', 'fixed': False, 'global': True, 'counties': None, 'launchYear': None, 'types': ['Public']}, {'date': '2010-05-13', 'localName': 'Ascension', 'name': 'Ascension Day', 'countryCode': 'FR', 'fixed': False, 'global': True, 'counties': None, 'launchYear': None, 'types': ['Public']}, {'date': '2010-05-24', 'localName': 'Lundi de Pentec\u00f4te', 'name': 'Whit Monday', 'countryCode': 'FR', 'fixed': False, 'global': True, 'counties': None, 'launchYear': None, 'types': ['Public']}, {'date': '2010-07-14', 'localName': 'F\u00eate nationale', 'name': 'Bastille Day', 'countryCode': 'FR', 'fixed': False, 'global': True, 'counties': None, 'launchYear': None, 'types': ['Public']}, {'date': '2010-08-15', 'localName': 'Assomption', 'name': 'Assumption Day', 'countryCode': 'FR', 'fixed': False, 'global': True, 'counties': None, 'launchYear': None, 'types': ['Public']}, {'date': '2010-11-01', 'localName': 'Toussaint', 'name': \"All Saints' Day\", 'countryCode': 'FR', 'fixed': False, 'global': True, 'counties': None, 'launchYear': None, 'types': ['Public']}, {'date': '2010-11-11', 'localName': 'Armistice 1918', 'name': 'Armistice Day', 'countryCode': 'FR', 'fixed': False, 'global': True, 'counties': None, 'launchYear': None, 'types': ['Public']}, {'date': '2010-12-25', 'localName': 'No\u00ebl', 'name': 'Christmas Day', 'countryCode': 'FR', 'fixed': False, 'global': True, 'counties': None, 'launchYear': None, 'types': ['Public']}]."], "error_type": "executable_checker:wrong_result", "prompt": {"question": "As a cultural anthropologist, you are studying the celebration of holidays in different countries during various years. You have a list of years and countries and you are using the 'retrieve_holiday_by_year' function to find the corresponding holidays. Could you identify the holidays celebrated in France in 2010?", "function": {"name": "retrieve_holiday_by_year", "description": "Finds the holidays of a year.", "parameters": {"type": "dict", "properties": {"year": {"type": "string", "description": "The year of the holidays."}, "country": {"type": "string", "description": "The country of the holidays. Possible options: US, AT, DE, ES, FR, GB, IT, NL, PL, RO, SK, UA."}}, "required": ["year", "country"]}}, "execution_result": [[{"date": "2010-01-01", "localName": "Jour de l'an", "name": "New Year's Day", "countryCode": "FR", "fixed": true, "global": true, "counties": null, "launchYear": 1967, "types": ["Public"]}, {"date": "2010-04-05", "localName": "Lundi de P\u00e2ques", "name": "Easter Monday", "countryCode": "FR", "fixed": false, "global": true, "counties": null, "launchYear": 1642, "types": ["Public"]}, {"date": "2010-05-01", "localName": "F\u00eate du Travail", "name": "Labour Day", "countryCode": "FR", "fixed": true, "global": true, "counties": null, "launchYear": null, "types": ["Public"]}, {"date": "2010-05-08", "localName": "Victoire 1945", "name": "Victory in Europe Day", "countryCode": "FR", "fixed": true, "global": true, "counties": null, "launchYear": null, "types": ["Public"]}, {"date": "2010-05-13", "localName": "Ascension", "name": "Ascension Day", "countryCode": "FR", "fixed": false, "global": true, "counties": null, "launchYear": null, "types": ["Public"]}, {"date": "2010-05-24", "localName": "Lundi de Pentec\u00f4te", "name": "Whit Monday", "countryCode": "FR", "fixed": false, "global": true, "counties": null, "launchYear": null, "types": ["Public"]}, {"date": "2010-07-14", "localName": "F\u00eate nationale", "name": "Bastille Day", "countryCode": "FR", "fixed": true, "global": true, "counties": null, "launchYear": null, "types": ["Public"]}, {"date": "2010-08-15", "localName": "Assomption", "name": "Assumption Day", "countryCode": "FR", "fixed": true, "global": true, "counties": null, "launchYear": null, "types": ["Public"]}, {"date": "2010-11-01", "localName": "Toussaint", "name": "All Saints' Day", "countryCode": "FR", "fixed": true, "global": true, "counties": null, "launchYear": null, "types": ["Public"]}, {"date": "2010-11-11", "localName": "Armistice 1918", "name": "Armistice Day", "countryCode": "FR", "fixed": true, "global": true, "counties": null, "launchYear": null, "types": ["Public"]}, {"date": "2010-12-25", "localName": "No\u00ebl", "name": "Christmas Day", "countryCode": "FR", "fixed": true, "global": true, "counties": null, "launchYear": null, "types": ["Public"]}]], "execution_result_type": "exact_match"}, "model_result_raw": "[retrieve_holiday_by_year(year='2010', country='FR')]", "model_result_decoded": ["retrieve_holiday_by_year(year='2010',country='FR')"]}
{"id": 78, "model_name": "gpt-3.5-turbo-0125", "test_category": "executable_simple", "valid": false, "error": ["Wrong execution result for: \"retrieve_holiday_by_year(year='2005',country='DE')\". Expected: [{'date': '2005-01-01', 'localName': 'Neujahr', 'name': \"New Year's Day\", 'countryCode': 'DE', 'fixed': True, 'global': True, 'counties': None, 'launchYear': 1967, 'types': ['Public']}, {'date': '2005-01-06', 'localName': 'Heilige Drei K\u00f6nige', 'name': 'Epiphany', 'countryCode': 'DE', 'fixed': True, 'global': False, 'counties': ['DE-BW', 'DE-BY', 'DE-ST'], 'launchYear': 1967, 'types': ['Public']}, {'date': '2005-03-25', 'localName': 'Karfreitag', 'name': 'Good Friday', 'countryCode': 'DE', 'fixed': False, 'global': True, 'counties': None, 'launchYear': None, 'types': ['Public']}, {'date': '2005-03-27', 'localName': 'Ostersonntag', 'name': 'Easter Sunday', 'countryCode': 'DE', 'fixed': False, 'global': False, 'counties': ['DE-BB', 'DE-HE'], 'launchYear': None, 'types': ['Public']}, {'date': '2005-03-28', 'localName': 'Ostermontag', 'name': 'Easter Monday', 'countryCode': 'DE', 'fixed': False, 'global': True, 'counties': None, 'launchYear': 1642, 'types': ['Public']}, {'date': '2005-05-01', 'localName': 'Tag der Arbeit', 'name': 'Labour Day', 'countryCode': 'DE', 'fixed': True, 'global': True, 'counties': None, 'launchYear': None, 'types': ['Public']}, {'date': '2005-05-05', 'localName': 'Christi Himmelfahrt', 'name': 'Ascension Day', 'countryCode': 'DE', 'fixed': False, 'global': True, 'counties': None, 'launchYear': None, 'types': ['Public']}, {'date': '2005-05-15', 'localName': 'Pfingstsonntag', 'name': 'Pentecost', 'countryCode': 'DE', 'fixed': False, 'global': False, 'counties': ['DE-BB', 'DE-HE'], 'launchYear': None, 'types': ['Public']}, {'date': '2005-05-16', 'localName': 'Pfingstmontag', 'name': 'Whit Monday', 'countryCode': 'DE', 'fixed': False, 'global': True, 'counties': None, 'launchYear': None, 'types': ['Public']}, {'date': '2005-05-26', 'localName': 'Fronleichnam', 'name': 'Corpus Christi', 'countryCode': 'DE', 'fixed': False, 'global': False, 'counties': ['DE-BW', 'DE-BY', 'DE-HE', 'DE-NW', 'DE-RP', 'DE-SL'], 'launchYear': None, 'types': ['Public']}, {'date': '2005-08-15', 'localName': 'Mari\u00e4 Himmelfahrt', 'name': 'Assumption Day', 'countryCode': 'DE', 'fixed': True, 'global': False, 'counties': ['DE-SL'], 'launchYear': None, 'types': ['Public']}, {'date': '2005-10-03', 'localName': 'Tag der Deutschen Einheit', 'name': 'German Unity Day', 'countryCode': 'DE', 'fixed': True, 'global': True, 'counties': None, 'launchYear': None, 'types': ['Public']}, {'date': '2005-10-31', 'localName': 'Reformationstag', 'name': 'Reformation Day', 'countryCode': 'DE', 'fixed': True, 'global': False, 'counties': ['DE-BB', 'DE-MV', 'DE-SN', 'DE-ST', 'DE-TH'], 'launchYear': None, 'types': ['Public']}, {'date': '2005-11-01', 'localName': 'Allerheiligen', 'name': \"All Saints' Day\", 'countryCode': 'DE', 'fixed': True, 'global': False, 'counties': ['DE-BW', 'DE-BY', 'DE-NW', 'DE-RP', 'DE-SL'], 'launchYear': None, 'types': ['Public']}, {'date': '2005-11-16', 'localName': 'Bu\u00df- und Bettag', 'name': 'Repentance and Prayer Day', 'countryCode': 'DE', 'fixed': False, 'global': False, 'counties': ['DE-SN'], 'launchYear': None, 'types': ['Public']}, {'date': '2005-12-25', 'localName': 'Erster Weihnachtstag', 'name': 'Christmas Day', 'countryCode': 'DE', 'fixed': True, 'global': True, 'counties': None, 'launchYear': None, 'types': ['Public']}, {'date': '2005-12-26', 'localName': 'Zweiter Weihnachtstag', 'name': \"St. Stephen's Day\", 'countryCode': 'DE', 'fixed': True, 'global': True, 'counties': None, 'launchYear': None, 'types': ['Public']}], but got: [{'date': '2005-01-01', 'localName': 'Neujahr', 'name': \"New Year's Day\", 'countryCode': 'DE', 'fixed': False, 'global': True, 'counties': None, 'launchYear': None, 'types': ['Public']}, {'date': '2005-01-06', 'localName': 'Heilige Drei K\u00f6nige', 'name': 'Epiphany', 'countryCode': 'DE', 'fixed': False, 'global': False, 'counties': ['DE-BW', 'DE-BY', 'DE-ST'], 'launchYear': None, 'types': ['Public']}, {'date': '2005-03-25', 'localName': 'Karfreitag', 'name': 'Good Friday', 'countryCode': 'DE', 'fixed': False, 'global': True, 'counties': None, 'launchYear': None, 'types': ['Public']}, {'date': '2005-03-27', 'localName': 'Ostersonntag', 'name': 'Easter Sunday', 'countryCode': 'DE', 'fixed': False, 'global': False, 'counties': ['DE-BB'], 'launchYear': None, 'types': ['Public']}, {'date': '2005-03-28', 'localName': 'Ostermontag', 'name': 'Easter Monday', 'countryCode': 'DE', 'fixed': False, 'global': True, 'counties': None, 'launchYear': None, 'types': ['Public']}, {'date': '2005-05-01', 'localName': 'Tag der Arbeit', 'name': 'Labour Day', 'countryCode': 'DE', 'fixed': False, 'global': True, 'counties': None, 'launchYear': None, 'types': ['Public']}, {'date': '2005-05-05', 'localName': 'Christi Himmelfahrt', 'name': 'Ascension Day', 'countryCode': 'DE', 'fixed': False, 'global': True, 'counties': None, 'launchYear': None, 'types': ['Public']}, {'date': '2005-05-15', 'localName': 'Pfingstsonntag', 'name': 'Pentecost', 'countryCode': 'DE', 'fixed': False, 'global': False, 'counties': ['DE-BB', 'DE-HE'], 'launchYear': None, 'types': ['Public']}, {'date': '2005-05-16', 'localName': 'Pfingstmontag', 'name': 'Whit Monday', 'countryCode': 'DE', 'fixed': False, 'global': True, 'counties': None, 'launchYear': None, 'types': ['Public']}, {'date': '2005-05-26', 'localName': 'Fronleichnam', 'name': 'Corpus Christi', 'countryCode': 'DE', 'fixed': False, 'global': False, 'counties': ['DE-BW', 'DE-BY', 'DE-HE', 'DE-NW', 'DE-RP', 'DE-SL'], 'launchYear': None, 'types': ['Public']}, {'date': '2005-08-15', 'localName': 'Mari\u00e4 Himmelfahrt', 'name': 'Assumption Day', 'countryCode': 'DE', 'fixed': False, 'global': False, 'counties': ['DE-SL'], 'launchYear': None, 'types': ['Public']}, {'date': '2005-10-03', 'localName': 'Tag der Deutschen Einheit', 'name': 'German Unity Day', 'countryCode': 'DE', 'fixed': False, 'global': True, 'counties': None, 'launchYear': None, 'types': ['Public']}, {'date': '2005-10-31', 'localName': 'Reformationstag', 'name': 'Reformation Day', 'countryCode': 'DE', 'fixed': False, 'global': False, 'counties': ['DE-BB', 'DE-MV', 'DE-SN', 'DE-ST', 'DE-TH'], 'launchYear': None, 'types': ['Public']}, {'date': '2005-11-01', 'localName': 'Allerheiligen', 'name': \"All Saints' Day\", 'countryCode': 'DE', 'fixed': False, 'global': False, 'counties': ['DE-BW', 'DE-BY', 'DE-NW', 'DE-RP', 'DE-SL'], 'launchYear': None, 'types': ['Public']}, {'date': '2005-11-16', 'localName': 'Bu\u00df- und Bettag', 'name': 'Repentance and Prayer Day', 'countryCode': 'DE', 'fixed': False, 'global': False, 'counties': ['DE-SN'], 'launchYear': None, 'types': ['Public']}, {'date': '2005-12-25', 'localName': 'Erster Weihnachtstag', 'name': 'Christmas Day', 'countryCode': 'DE', 'fixed': False, 'global': True, 'counties': None, 'launchYear': None, 'types': ['Public']}, {'date': '2005-12-26', 'localName': 'Zweiter Weihnachtstag', 'name': \"St. Stephen's Day\", 'countryCode': 'DE', 'fixed': False, 'global': True, 'counties': None, 'launchYear': None, 'types': ['Public']}]."], "error_type": "executable_checker:wrong_result", "prompt": {"question": "As a historian, you are researching the cultural practices of different European countries in the year 2005. You are particularly interested in the holidays celebrated in these countries during this year. You have access to the 'retrieve_holiday_by_year' function. Can you use this function with the 'year' parameter as '2005' and the 'country' parameter as 'DE' to find out the holidays celebrated in Germany in 2005?", "function": {"name": "retrieve_holiday_by_year", "description": "Finds the holidays of a year.", "parameters": {"type": "dict", "properties": {"year": {"type": "string", "description": "The year of the holidays."}, "country": {"type": "string", "description": "The country of the holidays. Possible options: US, AT, DE, ES, FR, GB, IT, NL, PL, RO, SK, UA."}}, "required": ["year", "country"]}}, "execution_result": [[{"date": "2005-01-01", "localName": "Neujahr", "name": "New Year's Day", "countryCode": "DE", "fixed": true, "global": true, "counties": null, "launchYear": 1967, "types": ["Public"]}, {"date": "2005-01-06", "localName": "Heilige Drei K\u00f6nige", "name": "Epiphany", "countryCode": "DE", "fixed": true, "global": false, "counties": ["DE-BW", "DE-BY", "DE-ST"], "launchYear": 1967, "types": ["Public"]}, {"date": "2005-03-25", "localName": "Karfreitag", "name": "Good Friday", "countryCode": "DE", "fixed": false, "global": true, "counties": null, "launchYear": null, "types": ["Public"]}, {"date": "2005-03-27", "localName": "Ostersonntag", "name": "Easter Sunday", "countryCode": "DE", "fixed": false, "global": false, "counties": ["DE-BB", "DE-HE"], "launchYear": null, "types": ["Public"]}, {"date": "2005-03-28", "localName": "Ostermontag", "name": "Easter Monday", "countryCode": "DE", "fixed": false, "global": true, "counties": null, "launchYear": 1642, "types": ["Public"]}, {"date": "2005-05-01", "localName": "Tag der Arbeit", "name": "Labour Day", "countryCode": "DE", "fixed": true, "global": true, "counties": null, "launchYear": null, "types": ["Public"]}, {"date": "2005-05-05", "localName": "Christi Himmelfahrt", "name": "Ascension Day", "countryCode": "DE", "fixed": false, "global": true, "counties": null, "launchYear": null, "types": ["Public"]}, {"date": "2005-05-15", "localName": "Pfingstsonntag", "name": "Pentecost", "countryCode": "DE", "fixed": false, "global": false, "counties": ["DE-BB", "DE-HE"], "launchYear": null, "types": ["Public"]}, {"date": "2005-05-16", "localName": "Pfingstmontag", "name": "Whit Monday", "countryCode": "DE", "fixed": false, "global": true, "counties": null, "launchYear": null, "types": ["Public"]}, {"date": "2005-05-26", "localName": "Fronleichnam", "name": "Corpus Christi", "countryCode": "DE", "fixed": false, "global": false, "counties": ["DE-BW", "DE-BY", "DE-HE", "DE-NW", "DE-RP", "DE-SL"], "launchYear": null, "types": ["Public"]}, {"date": "2005-08-15", "localName": "Mari\u00e4 Himmelfahrt", "name": "Assumption Day", "countryCode": "DE", "fixed": true, "global": false, "counties": ["DE-SL"], "launchYear": null, "types": ["Public"]}, {"date": "2005-10-03", "localName": "Tag der Deutschen Einheit", "name": "German Unity Day", "countryCode": "DE", "fixed": true, "global": true, "counties": null, "launchYear": null, "types": ["Public"]}, {"date": "2005-10-31", "localName": "Reformationstag", "name": "Reformation Day", "countryCode": "DE", "fixed": true, "global": false, "counties": ["DE-BB", "DE-MV", "DE-SN", "DE-ST", "DE-TH"], "launchYear": null, "types": ["Public"]}, {"date": "2005-11-01", "localName": "Allerheiligen", "name": "All Saints' Day", "countryCode": "DE", "fixed": true, "global": false, "counties": ["DE-BW", "DE-BY", "DE-NW", "DE-RP", "DE-SL"], "launchYear": null, "types": ["Public"]}, {"date": "2005-11-16", "localName": "Bu\u00df- und Bettag", "name": "Repentance and Prayer Day", "countryCode": "DE", "fixed": false, "global": false, "counties": ["DE-SN"], "launchYear": null, "types": ["Public"]}, {"date": "2005-12-25", "localName": "Erster Weihnachtstag", "name": "Christmas Day", "countryCode": "DE", "fixed": true, "global": true, "counties": null, "launchYear": null, "types": ["Public"]}, {"date": "2005-12-26", "localName": "Zweiter Weihnachtstag", "name": "St. Stephen's Day", "countryCode": "DE", "fixed": true, "global": true, "counties": null, "launchYear": null, "types": ["Public"]}]], "execution_result_type": "exact_match"}, "model_result_raw": "[retrieve_holiday_by_year(year='2005', country='DE')]", "model_result_decoded": ["retrieve_holiday_by_year(year='2005',country='DE')"]}
{"id": 85, "valid": false, "model_name": "gpt-3.5-turbo-0125", "test_category": "executable_simple", "error": ["Failed to decode executable. "], "error_type": "executable_decoder:decoder_failed", "prompt": {"question": "Can you find the maximum number of point that are in the same line out of all [[1,1],[2,2],[3,4],[5,5]].", "function": {"name": "maxPoints", "description": "Finds the maximum number of points on a line.", "parameters": {"type": "dict", "properties": {"points": {"type": "array", "items": {"type": "array", "items": {"type": "integer"}, "description": "A point represented by a 2 element list [x, y]."}, "description": "The list of points. Points are 2 element lists."}}, "required": ["points"]}}, "execution_result": [3], "execution_result_type": "exact_match"}, "model_result_raw": "[{'maxPoints': {'points': [[1,1],[2,2],[3,4],[5,5]]}}]"}
{"id": 87, "model_name": "gpt-3.5-turbo-0125", "test_category": "executable_simple", "valid": false, "error": ["Wrong execution result for: 'calculate_investment_value(initial_investment=10000,annual_contribution=1000,years=5,annual_return=5,inflation_rate=[1, 2, 3, 4, 4])'. Expected: 16145.646273400002, but got: 2371000."], "error_type": "executable_checker:wrong_result", "prompt": {"question": "Calculate the investment value of 10000 initial investment and 1000 annual contribution for 5 years. With an interest rate of 5% and inflation rate of [1%,2%,3%,4%,4%].", "function": {"name": "calculate_investment_value", "description": "Calculates the value of an investment over time.", "parameters": {"type": "dict", "properties": {"initial_investment": {"type": "integer", "description": "The initial investment amount."}, "annual_contribution": {"type": "integer", "description": "The annual contribution amount."}, "years": {"type": "integer", "description": "The number of years to calculate the investment value for."}, "annual_return": {"type": "float", "description": "The annual return rate in percentage."}, "inflation_rate": {"type": "array", "items": {"type": "float"}, "description": "The inflation rate for each year in percentage."}, "adjust_for_inflation": {"type": "boolean", "default": true, "description": "Whether to adjust the investment value for inflation."}}, "required": ["initial_investment", "annual_contribution", "years", "annual_return", "inflation_rate"]}}, "execution_result": [16145.646273400002], "execution_result_type": "exact_match"}, "model_result_raw": "[calculate_investment_value(initial_investment=10000, annual_contribution=1000, years=5, annual_return=5, inflation_rate=[1,2,3,4,4])]", "model_result_decoded": ["calculate_investment_value(initial_investment=10000,annual_contribution=1000,years=5,annual_return=5,inflation_rate=[1, 2, 3, 4, 4])"]}
{"id": 88, "model_name": "gpt-3.5-turbo-0125", "test_category": "executable_simple", "valid": false, "error": ["Wrong execution result for: 'calculate_investment_value(initial_investment=1000000,annual_contribution=1000,years=3,annual_return=0.1,inflation_rate=[0.01, 0.04, 0.04])'. Expected: 1063843.4989999998, but got: 1227813.9640000002."], "error_type": "executable_checker:wrong_result", "prompt": {"question": "Calculate the investment value of 1 million initial investment and 1k annual contribution for 3 years. With an interest rate of 10% and inflation rate of [1%,4%,4%].", "function": {"name": "calculate_investment_value", "description": "Calculates the value of an investment over time.", "parameters": {"type": "dict", "properties": {"initial_investment": {"type": "integer", "description": "The initial investment amount."}, "annual_contribution": {"type": "integer", "description": "The annual contribution amount."}, "years": {"type": "integer", "description": "The number of years to calculate the investment value for."}, "annual_return": {"type": "float", "description": "The annual return rate in percentage."}, "inflation_rate": {"type": "array", "items": {"type": "float"}, "description": "The inflation rate for each year in percentage."}, "adjust_for_inflation": {"type": "boolean", "default": true, "description": "Whether to adjust the investment value for inflation."}}, "required": ["initial_investment", "annual_contribution", "years", "annual_return", "inflation_rate"]}}, "execution_result": [1063843.4989999998], "execution_result_type": "exact_match"}, "model_result_raw": "[calculate_investment_value(initial_investment=1000000, annual_contribution=1000, years=3, annual_return=0.10, inflation_rate=[0.01, 0.04, 0.04])]", "model_result_decoded": ["calculate_investment_value(initial_investment=1000000,annual_contribution=1000,years=3,annual_return=0.1,inflation_rate=[0.01, 0.04, 0.04])"]}
{"id": 92, "model_name": "gpt-3.5-turbo-0125", "test_category": "executable_simple", "valid": false, "error": ["Wrong execution result for: \"book_room(room_type='king',price=10000,check_in_date='12-11-2023',check_out_date='08-15-2024',customer_id='123')\". Expected: {'customer_id': '123', 'room_number': 'king', 'check_in_date': '12-11-2023', 'check_out_date': '08-15-2024', 'total_price': 1000}, but got: {'customer_id': '123', 'room_number': 'king', 'check_in_date': '12-11-2023', 'check_out_date': '08-15-2024', 'total_price': 10000}."], "error_type": "executable_checker:wrong_result", "prompt": {"question": "Book a king room of 10000 dollar from Dec.11,2023, to Aug.15,2024, with customer id 123.", "function": {"name": "book_room", "description": "Books a room for a customer.", "parameters": {"type": "dict", "properties": {"room_type": {"type": "string", "description": "The room type to book."}, "price": {"type": "float", "description": "The price of the room. Default 0.0"}, "check_in_date": {"type": "string", "description": "The check-in date in format of MM-DD-YYYY. "}, "check_out_date": {"type": "string", "description": "The check-out date in format of MM-DD-YYYY."}, "customer_id": {"type": "string", "description": "The customer ID."}, "discount_code": {"type": "string", "description": "The discount code (if any).", "default": null}}, "required": ["room_type", "check_in_date", "check_out_date", "customer_id"]}}, "execution_result": [{"customer_id": "123", "room_number": "king", "check_in_date": "12-11-2023", "check_out_date": "08-15-2024", "total_price": 1000}], "execution_result_type": "exact_match"}, "model_result_raw": "[book_room(room_type='king', price=10000, check_in_date='12-11-2023', check_out_date='08-15-2024', customer_id='123')]", "model_result_decoded": ["book_room(room_type='king',price=10000,check_in_date='12-11-2023',check_out_date='08-15-2024',customer_id='123')"]}
{"id": 95, "model_name": "gpt-3.5-turbo-0125", "test_category": "executable_simple", "valid": false, "error": ["Error in execution: \"get_movie_director(movie_name='Avatar')\". Error: 'Director'"], "error_type": "executable_checker:execution_error", "prompt": {"question": "What's the director of Avatar.", "function": {"name": "get_movie_director", "description": "Fetches the director of a movie from the OMDB API.", "parameters": {"type": "dict", "properties": {"movie_name": {"type": "string", "description": "The name of the movie."}}, "required": ["movie_name"]}}, "execution_result": ["James Cameron"], "execution_result_type": "exact_match"}, "model_result_raw": "[get_movie_director(movie_name=\"Avatar\")]", "model_result_decoded": ["get_movie_director(movie_name='Avatar')"]}
{"id": 96, "model_name": "gpt-3.5-turbo-0125", "test_category": "executable_simple", "valid": false, "error": ["Error in execution: \"get_movie_director(movie_name='Pulp Fiction')\". Error: 'Director'"], "error_type": "executable_checker:execution_error", "prompt": {"question": "What's the director of Pulp Fiction.", "function": {"name": "get_movie_director", "description": "Fetches the director of a movie from the OMDB API.", "parameters": {"type": "dict", "properties": {"movie_name": {"type": "string", "description": "The name of the movie."}}, "required": ["movie_name"]}}, "execution_result": ["Quentin Tarantino"], "execution_result_type": "exact_match"}, "model_result_raw": "[get_movie_director(movie_name=\"Pulp Fiction\")]", "model_result_decoded": ["get_movie_director(movie_name='Pulp Fiction')"]}
{"id": 97, "model_name": "gpt-3.5-turbo-0125", "test_category": "executable_simple", "valid": false, "error": ["Error in execution: \"get_movie_rating(movie_name='Avatar')\". Error: 'Rated'"], "error_type": "executable_checker:execution_error", "prompt": {"question": "What's the age limit rating of Avatar.", "function": {"name": "get_movie_rating", "description": "Fetches the age rating of a movie from the OMDB API.", "parameters": {"type": "dict", "properties": {"movie_name": {"type": "string", "description": "The name of the movie."}}, "required": ["movie_name"]}}, "execution_result": ["PG-13"], "execution_result_type": "exact_match"}, "model_result_raw": "[get_movie_rating(movie_name=\"Avatar\")]", "model_result_decoded": ["get_movie_rating(movie_name='Avatar')"]}
{"id": 98, "model_name": "gpt-3.5-turbo-0125", "test_category": "executable_simple", "valid": false, "error": ["Error in execution: \"get_movie_rating(movie_name='Pulp Fiction')\". Error: 'Rated'"], "error_type": "executable_checker:execution_error", "prompt": {"question": "What's the age limit rating of Pulp Fiction.", "function": {"name": "get_movie_rating", "description": "Fetches the age rating of a movie from the OMDB API.", "parameters": {"type": "dict", "properties": {"movie_name": {"type": "string", "description": "The name of the movie."}}, "required": ["movie_name"]}}, "execution_result": ["R"], "execution_result_type": "exact_match"}, "model_result_raw": "[get_movie_rating(movie_name=\"Pulp Fiction\")]", "model_result_decoded": ["get_movie_rating(movie_name='Pulp Fiction')"]}
{"id": 100, "valid": false, "model_name": "gpt-3.5-turbo-0125", "test_category": "executable_simple", "error": ["Failed to decode executable. "], "error_type": "executable_decoder:decoder_failed", "prompt": {"question": "What is the are of polygon formed by vertices [[1,2],[3,4],[1,4],[3,7]]", "function": {"name": "polygon_area", "description": "Calculate the area of a polygon given its vertices using the shoelace formula.", "parameters": {"type": "dict", "properties": {"vertices": {"type": "array", "items": {"type": "array", "items": {"type": "integer"}, "description": "A single vertex represented by a 2 element list [x, y]."}, "description": "The vertices of the polygon, where each vertex is a 2 element list [x, y]."}}, "required": ["vertices"]}}, "execution_result": [0.0], "execution_result_type": "exact_match"}, "model_result_raw": "[{'name': 'polygon_area', 'parameters': {'vertices': [[1,2],[3,4],[1,4],[3,7]]}}]"}